plot4gmns/__init__.py
plot4gmns/_model.py
plot4gmns/func_lib.py
plot4gmns/network.py
plot4gmns/plot4gmns.py
plot4gmns/utility_lib.py
plot4gmns-0.1.3.dist-info/LICENSE
plot4gmns-0.1.3.dist-info/METADATA
plot4gmns-0.1.3.dist-info/WHEEL
plot4gmns-0.1.3.dist-info/top_level.txt
plot4gmns-0.1.3.dist-info/RECORD
