Metadata-Version: 2.1
Name: plot4gmns
Version: 0.1.3
Summary: Plot4GMNS: An open-source academic research tool for visualizing multimodal networks for transportation system modeling and optimization
Home-page: https://github.com/xyluo25/plot4gmns
Author: Dr. Junhua Chen, Zanyang Cui, Xiangyong Luo
Author-email: cjh@bjtu.edu.cn, zanyangcui@outlook.com, luoxiangyong01@gmail.com
Project-URL: Homepage, https://github.com/asu-trans-ai-lab/plot4gmns
Project-URL: Documentation, https://github.com/asu-trans-ai-lab/plot4gmns
Classifier: Programming Language :: Python :: 3
Classifier: License :: OSI Approved :: Apache Software License
Classifier: Operating System :: OS Independent
Requires-Python: >=3.9
License-File: LICENSE
Requires-Dist: keplergl (==0.3.2)
Requires-Dist: matplotlib (==3.4.3)
Requires-Dist: numpy (==1.20.3)
Requires-Dist: pandas
Requires-Dist: seaborn (==0.11.2)
Requires-Dist: Shapely (==2.0.0)
